toydb/Database.py
toydb/RowStruct.py
toydb/__init__.py
toydb/dtypes.py
toydb/exceptions.py
toydb/util.py
toydb-0.1.0.dist-info/LICENSE
toydb-0.1.0.dist-info/METADATA
toydb-0.1.0.dist-info/WHEEL
toydb-0.1.0.dist-info/top_level.txt
toydb-0.1.0.dist-info/RECORD
