Metadata-Version: 2.1
Name: toydb
Version: 0.1.0
Summary: A small, toy database written in pure python.
Home-page: https://github.com/a-poor/toydb
Author: Austin Poor
Author-email: austinpoor@gmail.com
License: UNKNOWN
Platform: UNKNOWN
Classifier: Programming Language :: Python :: 3.6
Classifier: Programming Language :: Python :: 3.7
Classifier: Programming Language :: Python :: 3.8
Classifier: License :: OSI Approved :: GNU General Public License v3 (GPLv3)
Classifier: Operating System :: OS Independent
Classifier: Topic :: Database
Classifier: Programming Language :: SQL
Classifier: Development Status :: 3 - Alpha
Requires-Python: >=3.6
